{"created_at": "Fri Apr 30 08:45:40 +0000 2021", "hashtags": [], "id": 1388051919373889537, "id_str": "1388051919373889537", "lang": "ja", "retweet_count": 1692, "retweeted_status": {"created_at": "Fri Apr 30 08:00:44 +0000 2021", "favorite_count": 8905, "hashtags": [], "id": 1388040609882013696, "id_str": "1388040609882013696", "lang": "ja", "retweet_count": 1692, "source": "<a href=\"https://cms.comnico.jp\" rel=\"nofollow\">MarketingSuite</a>", "text": "\ud83c\udfb5\u3044\u3088\u3044\u3088\u660e\u65e5\u767a\u58f2\ud83c\udfb5\n\u300cTinyTAN\u300d\u304cPUNYBEANS\u306e\u30c7\u30b6\u30a4\u30f3\u3067\u4e00\u756a\u304f\u3058\u306b\u521d\u767b\u5834\u203c\ufe0f\n\u53d6\u6271\u5e97\u8217\u3092\u4e8b\u524d\u306b\u30c1\u30a7\u30c3\u30af\ud83d\udc49https://t.co/gzUdygY3L4\n\n\u300e\u4e00\u756a\u304f\u3058 TinyTAN\u300f5\u67081\u65e5(\u571f)\u3088\u308a\u9806\u6b21\u767a\u58f2\u4e88\u5b9a\u2026 https://t.co/yfxd6XnrAZ", "truncated": true, "urls": [{"expanded_url": "https://bpnavi.jp/s/kuji/pc/ssc/search_pref/3223/prize", "url": "https://t.co/gzUdygY3L4"}, {"expanded_url": "https://twitter.com/i/web/status/1388040609882013696", "url": "https://t.co/yfxd6XnrAZ"}], "user": {"created_at": "Thu Nov 19 11:03:10 +0000 2009", "description": "\u300c\u4e00\u756a\u304f\u3058\u300d\u516c\u5f0f\u30a2\u30ab\u30a6\u30f3\u30c8\u3002\u65b0\u5546\u54c1&\u30ad\u30e3\u30f3\u30da\u30fc\u30f3\u60c5\u5831\u3092\u304a\u5c4a\u3051\u3057\u307e\u3059\uff01\u500b\u5225\u306e\u304a\u554f\u3044\u5408\u308f\u305b\u306b\u306f\u5bfe\u5fdc\u3057\u3066\u304a\u308a\u307e\u305b\u3093\u3002  \nInstagram\u21d2https://t.co/3wVhZJbjE3 \nfacebook\u21d2https://t.co/uBMTI0f0ll", "favourites_count": 77, "followers_count": 1319332, "friends_count": 19, "id": 91081573, "id_str": "91081573", "listed_count": 5433, "location": "\u65e5\u672c \u6771\u4eac", "name": "\u4e00\u756a\u304f\u3058\uff08BANDAI SPIRITS\uff09", "profile_background_color": "F5030F", "profile_background_image_url": "http://abs.twimg.com/images/themes/theme1/bg.png", "profile_background_image_url_https": "https://abs.twimg.com/images/themes/theme1/bg.png", "profile_banner_url": "https://pbs.twimg.com/profile_banners/91081573/1605170112", "profile_image_url": "http://pbs.twimg.com/profile_images/1326806106346172424/qZrQyvao_normal.jpg", "profile_image_url_https": "https://pbs.twimg.com/profile_images/1326806106346172424/qZrQyvao_normal.jpg", "profile_link_color": "F5030F", "profile_sidebar_border_color": "F5030F", "profile_sidebar_fill_color": "FFFFFF", "profile_text_color": "575057", "screen_name": "ichibanKUJI", "statuses_count": 1867359, "url": "http://t.co/leKFMK5Cqm", "verified": true, "withheld_in_countries": []}, "user_mentions": []}, "source": "<a href=\"http://twitter.com/download/iphone\" rel=\"nofollow\">Twitter for iPhone</a>", "text": "RT @ichibanKUJI: \ud83c\udfb5\u3044\u3088\u3044\u3088\u660e\u65e5\u767a\u58f2\ud83c\udfb5\n\u300cTinyTAN\u300d\u304cPUNYBEANS\u306e\u30c7\u30b6\u30a4\u30f3\u3067\u4e00\u756a\u304f\u3058\u306b\u521d\u767b\u5834\u203c\ufe0f\n\u53d6\u6271\u5e97\u8217\u3092\u4e8b\u524d\u306b\u30c1\u30a7\u30c3\u30af\ud83d\udc49https://t.co/gzUdygY3L4\n\n\u300e\u4e00\u756a\u304f\u3058 TinyTAN\u300f5\u67081\u65e5(\u571f)\u3088\u308a\u9806\u6b21\u767a\u58f2\u4e88\u5b9a\u203c\ufe0f\n\u8a73\u7d30\u306f\u21d2h\u2026", "urls": [{"expanded_url": "https://bpnavi.jp/s/kuji/pc/ssc/search_pref/3223/prize", "url": "https://t.co/gzUdygY3L4"}], "user": {"created_at": "Wed Sep 18 07:18:57 +0000 2013", "description": "#BTS JAPAN OFFICIAL Twitter", "followers_count": 10249559, "friends_count": 4, "id": 1878450026, "id_str": "1878450026", "listed_count": 17613, "name": "BTS JAPAN OFFICIAL", "profile_background_color": "89C9FA", "profile_background_image_url": "http://abs.twimg.com/images/themes/theme1/bg.png", "profile_background_image_url_https": "https://abs.twimg.com/images/themes/theme1/bg.png", "profile_banner_url": "https://pbs.twimg.com/profile_banners/1878450026/1619622103", "profile_image_url": "http://pbs.twimg.com/profile_images/1387421769984708612/RqvFFRu9_normal.jpg", "profile_image_url_https": "https://pbs.twimg.com/profile_images/1387421769984708612/RqvFFRu9_normal.jpg", "profile_link_color": "3B94D9", "profile_sidebar_border_color": "000000", "profile_sidebar_fill_color": "000000", "profile_text_color": "000000", "profile_use_background_image": true, "screen_name": "BTS_jp_official", "statuses_count": 3075, "url": "https://t.co/cTJdiKQzR9", "verified": true, "withheld_in_countries": []}, "user_mentions": [{"id": 91081573, "id_str": "91081573", "name": "\u4e00\u756a\u304f\u3058\uff08BANDAI SPIRITS\uff09", "screen_name": "ichibanKUJI"}]}
